mlfork/__init__.py
mlfork/auth.py
mlfork/client.py
mlfork/cmd.py
mlfork-0.0.1.dist-info/LICENSE
mlfork-0.0.1.dist-info/METADATA
mlfork-0.0.1.dist-info/WHEEL
mlfork-0.0.1.dist-info/entry_points.txt
mlfork-0.0.1.dist-info/top_level.txt
mlfork-0.0.1.dist-info/RECORD
