Metadata-Version: 2.1
Name: mlfork
Version: 0.0.1
Summary: Python package and CLI for interfacing with MLFork APIs
Home-page: https://github.com/mlfork/mlfork-python
Author: Nemanja Nikodijevic
Author-email: nemanja@mlfork.com
License: UNKNOWN
Platform: UNKNOWN
Classifier: Programming Language :: Python :: 3
Classifier: License :: OSI Approved :: MIT License
Classifier: Operating System :: OS Independent
Requires-Python: >=3.5
Requires-Dist: requests (>=2.22.0)
